zc.zope3recipes-1.0-py3.9-nspkg.pth
zc/zope3recipes/README.rst
zc/zope3recipes/WINDOWS.rst
zc/zope3recipes/__init__.py
zc/zope3recipes/ctl.py
zc/zope3recipes/debugzope.py
zc/zope3recipes/recipes.py
zc/zope3recipes/tests.py
zc/zope3recipes/winctl.py
zc.zope3recipes-1.0.dist-info/METADATA
zc.zope3recipes-1.0.dist-info/WHEEL
zc.zope3recipes-1.0.dist-info/entry_points.txt
zc.zope3recipes-1.0.dist-info/namespace_packages.txt
zc.zope3recipes-1.0.dist-info/top_level.txt
zc.zope3recipes-1.0.dist-info/RECORD
