Metadata-Version: 2.1
Name: zc.zope3recipes
Version: 1.0
Summary: ZC Buildout recipe for defining Zope 3 applications
Home-page: https://github.com/zopefoundation/zc.zope3recipes
Author: Jim Fulton
Author-email: zope-dev@zope.dev
License: ZPL 2.1
Keywords: zope3 buildout
Classifier: Development Status :: 5 - Production/Stable
Classifier: Framework :: Buildout
Classifier: Intended Audience :: Developers
Classifier: License :: OSI Approved :: Zope Public License
Classifier: Topic :: Software Development :: Build Tools
Classifier: Topic :: Software Development :: Libraries :: Python Modules
Classifier: Programming Language :: Python :: 3.7
Classifier: Programming Language :: Python :: 3.8
Classifier: Programming Language :: Python :: 3.9
Classifier: Programming Language :: Python :: 3.10
Classifier: Programming Language :: Python :: 3.11
Requires-Python: >=3.7
Requires-Dist: zc.buildout (>=1.2.0)
Requires-Dist: zope.testing
Requires-Dist: setuptools
Requires-Dist: zc.recipe.egg (>=1.2.0)
Requires-Dist: ZConfig (>=2.4a5)
Requires-Dist: pywin32 ; platform_system == "Windows"
Provides-Extra: test
Requires-Dist: zdaemon (>=3.0.0) ; extra == 'test'
Requires-Dist: zc.recipe.filestorage ; extra == 'test'
Requires-Dist: PasteScript ; extra == 'test'
